Workbook

Sheet 填写说明
B7: 产品岗举例
B8: 1. 选择对应岗位的表单进行填写（如没有对应的岗位表单，选择指标与评分标准相近的岗位表单填写）
B9: 2. 填写《产品岗明细》
B10: 3.检查《产品岗》中未映射事项并进行完善（《产品岗》与《产品明细》中部分有公式已直接映射）

Sheet 部门负责人
B1: 绩效评价表
B2: 姓名： 岗位： 部门：
B3: 评价维度 | C3: 权重（%） | D3: 成果总结 | E3: 自评 | F3: 上级评分 | G3: 最终得分 （上级评分*权重）
B4: 本部门重点项目贡献 | C4: 0.3 | D4: =部门负责人明细!H4 -> 0 | F4: =部门负责人明细!N4 -> 0 | G4: =F4*C4 -> 0
B5: 岗位核心职责完成情况 | C5: 0.4 | D5: =部门负责人明细!H7 -> 0 | F5: =部门负责人明细!N7 -> 0 | G5: =F5*C5 -> 0
B6: 价值观及行为（包括但不限于团队协作、扛责担当、客户导向、人才发展（包括带教新人、知识传承、自我学习与提升）等） | C6: 0.3 | D6: =部门负责人明细!H12 -> 0 | F6: =部门负责人明细!N12 -> 0 | G6: =F6*C6 -> 0
B7: 总分 | G7: =SUM(G4:G6) -> 0
B8: 员工签字： 签字日期： | D8: 直接上级签字： 签字日期：

Sheet 部门负责人明细
B1: 绩效评价表
B2: 姓名： 岗位： 部门：
B3: 评价维度 | C3: 整体权重 | D3: 绩效指标 | E3: 指标定义/说明 | F3: 权重（%） | G3: 目标值 | H3: 成果总结 | I3: 评分标准 | J3: 自评 （百分制） | K3: 上级评分（百分制） | L3: 部门评分（百分制） | M3: 得分 | N3: 总分
B4: 本部门重点项目贡献 | C4: 1 | D4: 重点项目目标达成率 | E4: 部门年度核心重点项目的目标落地与成果价值实现 | G4: 100 | I4: 1. 所有重点项目核心目标超额达成，成果对业务有显著增益（90-100 分） 2. 所有重点项目核心目标全部达成，成果完全符合预期（80-89 分） 3. 多数重点项目目标达成，仅个别项目略有差距且不影响整体（70-79 分） 4. 部分重点项目目标未达成，对整体价值有轻微影响（60-69 分） 5. 核心重点项目目标未达成，成果未实现核心价值（＜60 分） | M4: =J4*0.1+K4*0.9 -> 0 | N4: =(M4*F4+M5*F5)*0.8+L4*0.2 -> 0
D5: 重点项目资源统筹效率 | E5: 重点项目中内外部资源的调配、利用与协同效果 | G5: 100 | I5: 1. 资源调配精准高效，无闲置或短缺，全力支撑项目推进（90-100 分） 2. 资源调配合理，偶有微调但不影响项目整体节奏（80-89 分） 3. 资源调配基本适配，轻微问题可及时解决（70-79 分） 4. 资源调配存在偏差，对项目进度有一定影响（60-69 分） 5. 资源调配混乱，导致项目严重受阻或延期（＜60 分） | M5: =J5*0.1+K5*0.9 -> 0
B7: 岗位核心职责完成情况 | C7: 1 | D7: 部门年度任务完成率 | E7: 部门年度常规工作、核心 KPI 的整体完成效果 | G7: 100 | I7: 1. 所有任务高质量完成，部分工作超出预期要求（90-100 分） 2. 所有任务按标准完成，无质量或进度问题（80-89 分） 3. 多数任务顺利完成，仅少数存在轻微瑕疵（70-79 分） 4. 部分任务未完成，或完成质量有明显不足（60-69 分） 5. 多项核心任务未完成，整体效果未达基本要求（＜60 分） | M7: =J7*0.1+K7*0.9 -> 0 | N7: =(M7*F7+M8*F8+M9*F9+M10*F10)*0.8+L7*0.2 -> 0
D8: 团队核心成果交付质量 | E8: 部门团队输出核心成果的质量与内外部反馈 | G8: 100 | I8: 1. 成果质量突出，内外部客户高度认可（90-100 分） 2. 成果质量达标，内外部无任何负面反馈（80-89 分） 3. 成果质量基本合格，客户反馈无严重问题（70-79 分） 4. 成果质量有明显瑕疵，客户存在轻微不满（60-69 分） 5. 成果质量不达标，客户反馈负面且影响合作（＜60 分） | M8: =J8*0.1+K8*0.9 -> 0
D9: 部门运营合规性 | E9: 部门日常运营中预算、流程、风险防控的合规表现 | G9: 100 | I9: 1. 全年无任何合规问题，运营规范有序（90-100 分） 2. 仅存在极轻微疏漏，及时整改无任何影响（80-89 分） 3. 合规问题较少，整改及时未造成风险（70-79 分） 4. 存在一定合规问题，需重点关注并整改（60-69 分） 5. 合规问题严重，引发管理风险或资源损失（＜60 分） | M9: =J9*0.1+K9*0.9 -> 0
D10: 跨部门协同效率 | E10: 与其他部门协作的顺畅度、响应度与问题解决效果 | G10: 100 | I10: 1. 主动发起协同，快速响应需求，高效解决跨部门问题（90-100 分） 2. 积极配合协作，响应及时，跨部门事务顺利推进（80-89 分） 3. 配合完成必要协作，响应及时，问题基本解决（70-79 分） 4. 被动参与协作，响应滞后，跨部门问题解决不顺畅（60-69 分） 5. 抵触跨部门协作，响应迟缓，问题长期未解决（＜60 分） | M10: =J10*0.1+K10*0.9 -> 0
B12: 价值观及行为 | C12: 1 | D12: 团队引领与人才发展 | E12: 部门员工培养、梯队建设、士气激励的整体表现 | G12: 100 | I12: 1. 积极培养骨干人才，团队梯队清晰，士气高涨凝聚力强（90-100 分） 2. 重视人才培养，核心员工稳定，团队士气积极向上（80-89 分） 3. 完成基础人才带教，核心员工留存良好，团队氛围平稳（70-79 分） 4. 人才培养动作不足，带教效果一般，团队士气平淡（60-69 分） 5. 无人才培养意识，核心员工流失，团队士气低迷（＜60 分） | M12: =J12*0.1+K12*0.9 -> 0 | N12: =(M12*F12+M13*F13+M14*F14)*0.8+L12*0.2 -> 0
D13: 责任担当与决策力 | E13: 面对问题、突发状况的担当态度及决策落地效果 | G13: 100 | I13: 1. 主动承担责任，决策科学精准，落地效果超预期（90-100 分） 2. 不推诿责任，决策合理可行，落地效果完全达标（80-89 分） 3. 坚守自身责任，决策无明显失误，落地效果基本达标（70-79 分） 4. 偶尔推诿责任，决策存在小失误但无严重影响（60-69 分） 5. 频繁推卸责任，决策失误，给部门造成损失（＜60 分） | M13: =J13*0.1+K13*0.9 -> 0
D14: 文化传承与协作共赢 | E14: 践行公司核心价值观、推动部门文化及跨团队协作表现 | G14: 100 | I14: 1. 主动传播公司文化，牵头跨部门协作并获广泛认可（90-100 分） 2. 自觉践行文化要求，积极参与协作，无任何协作冲突（80-89 分） 3. 遵守文化规范，配合完成协作，无明显问题（70-79 分） 4. 文化践行不足，协作态度被动，存在轻微冲突（60-69 分） 5. 违背核心价值观，抵触协作，冲突频繁影响工作（＜60 分） | M14: =J14*0.1+K14*0.9 -> 0
B15: 总分 | M15: =N4*0.3+N7*0.4+N12*0.3 -> 0
B16: 员工签字： 签字日期： | I16: 直接上级签字： 签字日期：

Sheet 产品岗
B1: 绩效评价表
B2: 姓名： 岗位： 部门：
B3: 评价维度 | C3: 权重（%） | D3: 成果总结 | E3: 自评 | F3: 上级评分 | G3: 最终得分 （上级评分*权重）
B4: 本部门重点项目贡献 | C4: 0.3 | D4: =产品岗明细!H4 -> 0 | F4: =产品岗明细!N4 -> 0 | G4: =F4*C4 -> 0
B5: 岗位核心职责完成情况 | C5: 0.4 | D5: =产品岗明细!H8 -> 0 | F5: =产品岗明细!N8 -> 0 | G5: =F5*C5 -> 0
B6: 价值观及行为（包括但不限于团队协作、扛责担当、客户导向、人才发展（包括带教新人、知识传承、自我学习与提升）等） | C6: 0.3 | D6: =产品岗明细!H13 -> 0 | F6: =产品岗明细!N13 -> 0 | G6: =F6*C6 -> 0
B7: 总分 | G7: =SUM(G4:G6) -> 0
B8: 员工签字： 签字日期： | D8: 直接上级签字： 签字日期：

Sheet 产品岗明细
B1: 绩效评价表
B2: 姓名： 岗位： 部门：
B3: 评价维度 | C3: 绩效指标 | D3: 整体权重 | E3: 指标定义/说明 | F3: 权重（%） | G3: 目标值 | H3: 成果总结 | I3: 评分标准 | J3: 自评 （百分制） | K3: 上级评分（百分制） | L3: 部门评分 | M3: 得分 | N3: 总分
B4: 本部门重点项目贡献 | C4: 任务目标达成率 | D4: 1 | E4: 作为所负责需求产品经理，任务排期，按期保质达成项目评审工作（依据《产品工作任务书》 | G4: 100 | I4: 满分100：每项需求评审，明确需求内容与边界，完成需求分析（需求分析文档）、产品设计（产品原型、业务流程），确保产品目标最终按时达成。最终产品评审通过作为目标达成标准。 1：完成工作完成率，得到对应的分数。 2：工作评审等级为中、高级，评审次数大于2次，每次扣5分。 3：得分=完成率得分-评审扣分 4：此分值最高为100分。 | M4: =J4*0.1+K4*0.9 -> 0 | N4: =(M4*F4+M5*F5+M6*F6)*0.8+L4*0.2 -> 0
C5: 设计与文档输出 | E5: 按时保质完成设计（产品原型、流程图、需求分析），保证需求完整性和质量标准《设计规范标准》 | G5: 100 | I5: 满分100 1：设计完整，符合需求，符合设计标准，能够满足用户需求并具有创新性（90-100） 2：设计基本完整，需求基本满足，与设计标准匹配度较高，能够满足大部分用户需求（80-89） 3：设计基本完成，需求基本满足，与设计标准匹配度一般，能够满足部分用户需求（60-79） 4：设计不完整，需求未完全满足，与设计标准匹配度低，不能满足用户需求（50-59） 5：设计缺失严重，需求未满足，与设计标准匹配度极低，无法满足用户需求（0-49） | M5: =J5*0.1+K5*0.9 -> 0
C6: 知识分享 | E6: 自身针对战略、市场、产品、项目管理等分享 | G6: 100 | I6: 满分100： 1：分享大于等于1次，得100: 2：分享0次，得0分； | M6: =J6*0.1+K6*0.9 -> 0
B8: 岗位核心职责完成情况 | C8: 制度与规范执行 | D8: 1 | E8: 严格执行公司、部门制度与规范 | G8: 100 | I8: 满分100： 1:优严格执行公司和部门制度与规范，无违规行为，积极配合上级安排，绩效突出，对公司发展做出了重要贡献（90-100） 2:大部分时间严格执行公司和部门制度与规范，偶有违规行为但及时改正，工作表现稳定，对公司发展有一定贡献（80-89） 3:一般地执行公司和部门制度与规范，偶有违规行为，需要改进，工作表现一般，对公司发展贡献有限（60-79） 4:经常违反公司和部门制度与规范，严重影响团队和公司的正常运转，需要立即改进，工作表现较差，对公司发展没有贡献（50-59） 5:严重违反公司和部门制度与规范，严重影响公司形象和利益，造成重大损失，需要立即纠正，对公司发展没有任何贡献（0-49） | M8: =J8*0.1+K8*0.9 -> 0 | N8: =(M8*F8+M9*F9+M10*F10+F11*M11)*0.8+L8*0.2 -> 0
C9: 工作能力 | E9: 沟通能力 | G9: 100 | I9: 1：具有出色的口头沟通技巧，简明扼要，易于理解（90-100分） 2：口头沟通能够表达出意图，重点突出，较容易理解（80-89分） 3：口头沟通基本能够表达意图，重点比较突出，偶尔需要重复说明（70-79分） 4：口头表达语言组织欠清晰，但尚能表达出意图，有时需要反复解释（60-69分） 5：口头表达含糊其辞，根本表达不清（60分以下） | M9: =J9*0.1+K9*0.9 -> 0
E10: 执行能力 | G10: 100 | I10: 1：具有出色的执行力，无需上级指导，执行效果经常超出上级的想象（90-100分） 2：具有较强的执行力，在上级的指导下，能够完成任务，执行效果很好（80-89分） 3：执行力可满足岗位的要求，但缺乏独立思考和计划的能力，需要上级在方法上给予支持，执行效果较好（70-79分） 4：执行力一般，偶尔有推脱或畏难现象，执行过程经常需要上级的帮助，执行效果一般（60-69分） 5：初步具有执行意识，但执行延迟，经常出现推脱或畏难现象，需要特别关注和帮助，执行力较弱（60分以下） | M10: =J10*0.1+K10*0.9 -> 0
E11: 业务能力和水平 | G11: 100 | I11: 1：精通本岗位所要求的理论知识和专业技能（90-100分） 2：全面了解并较好的掌握与本岗位有关的理论知识和专业技能（80-89分） 3：基本掌握与本岗位有关的专业知识，对本岗位业务有一定了解，但尚需提高（70-79分） 4：对本岗位专业知识有一定了解，但不够深入（60-69分） 5：业务知识欠缺，业务生疏，经常出现失误（60分以下） | M11: =J11*0.1+K11*0.9 -> 0
B13: 价值观及行为 | C13: 工作态度 | D13: 1 | E13: 工作的态度 | G13: 100 | I13: 1：积极主动承担各种工作任务，完成过程中有自己的思考，可提出自己独到的想法（90-100分） 2：对于领导交待的任务不折不扣的执行，积极主动解决过程中的各种问题（80-89分） 3：对于领导交待的任务积极的执行，偶尔需要在领导的指导下才可顺利完成（70-79分） 4：对于领导交待的任务，大多接受的较为被动，需在领导的多次指导下才可完成（60-69分） 5：完全被动的接受任务，主动性欠缺，任务完成质量较差（60分以下） | M13: =J13*0.1+K13*0.9 -> 0 | N13: =(M13*F13+M14*F14+M15*F15+M16*F16+M17*F17)*0.8+L13*0.2 -> 0
C14: 团队协作 | E14: 主动配合团队工作、分享产品经验 / 知识（如内部分享、案例输出）、协助同事解决工作难题的表现 | G14: 100 | I14: 1：主动发起团队协作，高频分享有价值经验，积极协助同事解决复杂难题，成为团队协作核心角色（90-100分） 2：积极配合团队安排，主动分享经验，能协助同事解决常规难题，无协作推诿情况（80-89分） 3：配合团队基础协作要求，偶尔分享经验，同事求助时能提供基础协助，无明显协作问题（70-79分） 4：被动参与协作，较少分享经验，同事求助时响应消极，存在轻微协作推诿（60-69 分） 5：拒绝配合团队协作，不分享经验，回避同事求助，严重影响团队协作效率（60分以下） | M14: =J14*0.1+K14*0.9 -> 0
C15: 扛责担当 | E15: 面对工作问题（如需求偏差、项目风险）的态度，及关键任务的承接表现 | G15: 100 | I15: 1：主动发现并承担问题责任，积极推动解决方案，主动争抢关键 / 困难任务，不回避挑战（90-100分） 2：不推诿已发现的问题责任，能配合推动解决，关键任务安排后能积极承接，不抱怨（80-89分） 3：不主动承担额外责任，但自身负责范围内的问题不推诿，关键任务安排后能接受，无明显抵触（70-79分） 4：自身负责范围内的问题偶尔推诿，关键任务安排后被动接受，存在抱怨情绪（60-69 分） 5：频繁推诿各类问题责任，拒绝承接关键任务，回避工作挑战，影响任务推进（60分以下） | M15: =J15*0.1+K15*0.9 -> 0
C16: 客户导向 | E16: 关注业务方 / 用户需求，及基于反馈优化工作的表现 | G16: 100 | I16: 1：主动高频对接客户获取反馈，深度分析需求痛点，主动推动基于反馈的产品优化，获得客户高度认可（90-100分） 2：定期对接客户获取反馈，能分析反馈并推动基础优化，客户无负面评价（80-89分） 3：按要求对接客户获取反馈，能响应反馈并做简单调整，客户无明显负面评价（70-79分） 4：需提醒才对接客户，反馈收集不完整，仅部分响应反馈，客户存在轻微负面评价（60-69 分） 5. 拒绝对接客户，不收集反馈，无视客户需求，客户存在严重负面评价（60分以下） | M16: =J16*0.1+K16*0.9 -> 0
C17: 人才发展 | E17: 带教新人、自我学习提升、知识传承的综合表现 | G17: 100 | I17: 1：主动带教新人并帮助其快速成长，自主规划高频学习（如课程、行业研究），主动输出高质量知识文档，成为团队学习 / 传承标杆（90-100分） 2：按要求带教新人并帮助其达标，有固定学习计划（如定期课程），按要求输出知识文档，无明显不足（80-89分） 3：带教新人时能解答疑问，有基础学习行为，能配合输出简单知识文档，基本达标（70-79分） 4：带教新人时敷衍解答，学习行为零散无计划，知识文档需多次催促才输出，质量较差（60-69 分） 5：拒绝带教新人，无学习行为，不输出知识文档，阻碍团队人才发展 / 知识传承（60分以下） | M17: =J17*0.1+K17*0.9 -> 0
B18: 总分 | M18: =N4*0.3+N8*0.4+N13*0.3 -> 0
B19: 员工签字： 签字日期： | I19: 直接上级签字： 签字日期：

Sheet 研发岗
B1: 绩效评价表
B2: 姓名： 岗位： 部门：
B3: 评价维度 | C3: 权重（%） | D3: 成果总结 | E3: 自评 | F3: 上级评分 | G3: 最终得分 （上级评分*权重）
B4: 本部门重点项目贡献 | C4: 0.3 | D4: =研发岗明细!H4 -> 任务完成率：本季度个人主导并高质量完成 TMS 结算服务迁移（CHJY-23808）、结算信息支持修改回单付（CHJY-21625）、TMS 支持融合网货撮合运单（CHJY-25144）、服务大厅二级频道扩充（RZMP-8178）等核心需求，覆盖 TMS 结算平台、物流 Web 端、货主移动端、企服运营后台等多业务线，整体任务按计划完成率达 95% 以上，交付达成率 100%，所有需求均按期上线。 交付质量：主导 TMS 结算服务迁移，将客户对账、日常收支、在途费用等 42 个接口、5 大模块由老链路切换至独立 TMS 结算服务，设计接口级灰度开关配合三层静默兜底机制（开关异常、新服务异常、启动失败均自动回退老链路），实现 20 个页面组件零改动、仅 5 个列表页接入开关刷新，切换过程无业务中断；结算信息支持修改回单付（C147.9）为直接影响资金准确性的核心链路改造，通过 BigNumber 精度控制与触发来源区分，PC 与 H5 双端行为一致，上线后运行稳定无资金类事故；9 月独立承接企服线首个核心模块，从 0 搭建活动专区、智能体市场、行业资讯三个二级频道约 8000 行代码，采用模块化 + 可配置化架构，后续新增频道边际成本极低。上线后系统运行稳定，无重大生产事故。 | F4: =研发岗明细!N4 -> 0 | G4: =F4*C4 -> 0
B5: 岗位核心职责完成情况 | C5: 0.4 | D5: =研发岗明细!H7 -> 交付质量：本季度代码交付质量稳定，提测前均进行自测与 ESLint 校验，提测后无重大 Bug。TMS 结算服务迁移（CHJY-23808）与企服线服务大厅二级频道扩充（RZMP-8178）两项核心模块投入周期长、架构复杂度高，前者涉及 42 个接口的跨服务切换与历史重复接口治理，后者为从 0 搭建的新项目首个核心功能，两项交付后均运行稳定，无核心用户体验投诉。 专业技术与规范：迁移过程中主动阅读 @wlydfe/service 请求组装源码，确认两种接口前缀写法最终路径等价后统一在途费用重复定义的问题，收敛历史隐患；严格遵循开发规范执行全流程，需求改动同步维护改动清单与接口说明文档，TMS 迁移累计产出 5 份方案文档（含 42 个接口逐个标注服务与数据表的梳理表），技术文档完整准确且及时更新；主动与后端沟通对接，确保技术实现与业务目标高度对齐，流程合规度 100%。 | F5: =研发岗明细!N7 -> 0 | G5: =F5*C5 -> 0
B6: 价值观及行为（包括但不限于团队协作、扛责担当、客户导向、人才发展（包括带教新人、知识传承、自我学习与提升）等） | C6: 0.3 | D6: =研发岗明细!H12 -> 1. 责任心与协作： 主动承接 TMS 结算服务迁移（CHJY-23808）这一跨服务、跨团队的架构改造任务，独立完成 42 个接口的前端侧梳理与方案设计，逐个标注对应服务与数据表，输出交接文档作为前后端协作基准；积极配合产品、测试及后端同事，在后端服务拆分与网关配置期间主动同步进度、对齐风险，保障迁移平稳落地。 2. 主动思考与沟通： 针对服务迁移的全量切换风险，独立设计「接口级灰度开关 + 开关关/未命中/异常三层静默兜底」方案，并补充静默请求、并发去重、时间节流、启动不阻断等细节实现，将页面层改动收敛至 5 处；针对企服线二级频道的可扩展性要求，主动采用模块目录隔离 + 组合式函数复用的架构设计；延续 Q2 的 AI 辅助开发实践，将 AI 工具链从单一 Skill 扩展为覆盖需求分析、代码分析、代码审查、缺陷排查、知识沉淀的完整体系，并沉淀 12 篇研发流程 SOP 文档供团队使用。 3. 扛责担当与客户导向： 结算信息支持修改回单付（C147.9）涉及资金计算且需 PC/H5 双端行为一致，主动识别并处理浮点精度、异常数据、移动端键盘限制等多类边界问题；C169.6 融合网货撮合运单横跨 TMS PC 端、物流 Web 端、货主移动端三端并行交付，按业务方诉求快速响应多轮调整（期间需求调整类变更 11 次），保障功能按期上线。 4. 人才发展与知识传承： 保持高频学习与输出，主动梳理 TMS 结算迁移、企服线二级频道配置等新技术难点并形成改动清单、方案文档与改动清单；建立 AI 辅助开发四端规则同步与知识库自动生成机制，将知识库维护从手工转为脚本产出，降低团队重复劳动成本。 | F6: =研发岗明细!N12 -> 0 | G6: =F6*C6 -> 0
B7: 总分 | G7: =SUM(G4:G6) -> 0
B8: 员工签字： 签字日期： | D8: 直接上级签字： 签字日期：

Sheet 研发岗明细
B1: 绩效评价表
B2: 姓名： 王新骏 岗位： 高级前端开发 部门：物流服务交付事业群/业务平台事业部/前端部/结算前端组
B3: 评价维度 | C3: 绩效指标 | D3: 整体权重 | E3: 指标定义/说明 | F3: 权重（%） | G3: 目标值 | H3: 成果总结 | I3: 评分标准 | J3: 自评 （百分制） | K3: 上级评分（百分制） | L3: 部门评分 | M3: 得分 | N3: 总分
B4: 本部门重点项目贡献 | C4: 项目/任务指标 | D4: 1 | E4: 工作任务按计划、交付标准完成率 | G4: 100 | H4: 任务完成率：本季度个人主导并高质量完成 TMS 结算服务迁移（CHJY-23808）、结算信息支持修改回单付（CHJY-21625）、TMS 支持融合网货撮合运单（CHJY-25144）、服务大厅二级频道扩充（RZMP-8178）等核心需求，覆盖 TMS 结算平台、物流 Web 端、货主移动端、企服运营后台等多业务线，整体任务按计划完成率达 95% 以上，交付达成率 100%，所有需求均按期上线。 交付质量：主导 TMS 结算服务迁移，将客户对账、日常收支、在途费用等 42 个接口、5 大模块由老链路切换至独立 TMS 结算服务，设计接口级灰度开关配合三层静默兜底机制（开关异常、新服务异常、启动失败均自动回退老链路），实现 20 个页面组件零改动、仅 5 个列表页接入开关刷新，切换过程无业务中断；结算信息支持修改回单付（C147.9）为直接影响资金准确性的核心链路改造，通过 BigNumber 精度控制与触发来源区分，PC 与 H5 双端行为一致，上线后运行稳定无资金类事故；9 月独立承接企服线首个核心模块，从 0 搭建活动专区、智能体市场、行业资讯三个二级频道约 8000 行代码，采用模块化 + 可配置化架构，后续新增频道边际成本极低。上线后系统运行稳定，无重大生产事故。 | I4: 满分100：包含以下二项内容： （一）工作任务完成率满分70 1、工作任务按计划完成率大于90% 60-70 2、工作任务按计划完成率 80%-90% 50-59 3、工作任务按计划完成率 70%-80% 40-49 4、工作任务按计划完成率 小于70% 40以下 （二）工作质量 满分30分，每个重大缺陷扣10分 大于3次重大缺陷时，（一）（二）两项均记为0分 | J4: 98 | M4: =J4*0.1+K4*0.9 -> 9.8 | N4: =(M4*F4+M5*F5)*0.8+L4*0.2 -> 0
E5: 任务所属项目按计划、交付标准达成率 | G5: 100 | I5: 1、项目按时保质交付上线90-100 2、项目交付时间每次延迟时间小于10%扣5分，大于10%以上扣10分 说明：因新增，变更需求（PCR通过审核），按调整后的项目完成时间为准 | J5: 95 | M5: =J5*0.1+K5*0.9 -> 9.5
B7: 岗位核心职责完成情况 | C7: 交付质量 | D7: 1 | E7: 用户体验、生产问题 | G7: 100 | H7: 交付质量：本季度代码交付质量稳定，提测前均进行自测与 ESLint 校验，提测后无重大 Bug。TMS 结算服务迁移（CHJY-23808）与企服线服务大厅二级频道扩充（RZMP-8178）两项核心模块投入周期长、架构复杂度高，前者涉及 42 个接口的跨服务切换与历史重复接口治理，后者为从 0 搭建的新项目首个核心功能，两项交付后均运行稳定，无核心用户体验投诉。 专业技术与规范：迁移过程中主动阅读 @wlydfe/service 请求组装源码，确认两种接口前缀写法最终路径等价后统一在途费用重复定义的问题，收敛历史隐患；严格遵循开发规范执行全流程，需求改动同步维护改动清单与接口说明文档，TMS 迁移累计产出 5 份方案文档（含 42 个接口逐个标注服务与数据表的梳理表），技术文档完整准确且及时更新；主动与后端沟通对接，确保技术实现与业务目标高度对齐，流程合规度 100%。 | I7: 交付质量，满分100 无生产问题，无用户体验问题，90-100分； 不构成生产问题，但对用户体验有影响，80-89分； 造成关键功能、数据影响，但快速修复，60-79分； 造成生产线事故，60分以下 | J7: 95 | M7: =J7*0.1+K7*0.9 -> 9.5 | N7: =(M7*F7+M8*F8+M9*F9+M10*F10)*0.8+L7*0.2 -> 0
C8: 专业技术指标 | E8: 代码缺陷率，依据任务提测后的测试组提交的缺陷数量 | G8: 100 | I8: 满分100，超过目标值一个，至少扣10分，出现重大bug，至少扣20分 | J8: 98 | M8: =J8*0.1+K8*0.9 -> 9.8
E9: 技术文档（设计、接口文档\测试用例）的完整、有效、正确编制 | G9: 100 | I9: 满分100，每次不符合要求，至少扣5分 | J9: 95 | M9: =J9*0.1+K9*0.9 -> 9.5
C10: 流程规范 | E10: 工作流程、规范符合度 | G10: 100 | I10: 依据产研部发布的《工作流程、规范》要求，每次不符合规范流程，以规范中的扣分标准执行；规范中未明确的情况，根据实际情况补充发布的规范扣分 | J10: 96 | M10: =J10*0.1+K10*0.9 -> 9.6
B12: 价值观及行为 | C12: 责任心与协作 | D12: 1 | E12: 工作职责与分工、高效协作、执行力、主动性 | G12: 100 | H12: 1. 责任心与协作： 主动承接 TMS 结算服务迁移（CHJY-23808）这一跨服务、跨团队的架构改造任务，独立完成 42 个接口的前端侧梳理与方案设计，逐个标注对应服务与数据表，输出交接文档作为前后端协作基准；积极配合产品、测试及后端同事，在后端服务拆分与网关配置期间主动同步进度、对齐风险，保障迁移平稳落地。 2. 主动思考与沟通： 针对服务迁移的全量切换风险，独立设计「接口级灰度开关 + 开关关/未命中/异常三层静默兜底」方案，并补充静默请求、并发去重、时间节流、启动不阻断等细节实现，将页面层改动收敛至 5 处；针对企服线二级频道的可扩展性要求，主动采用模块目录隔离 + 组合式函数复用的架构设计；延续 Q2 的 AI 辅助开发实践，将 AI 工具链从单一 Skill 扩展为覆盖需求分析、代码分析、代码审查、缺陷排查、知识沉淀的完整体系，并沉淀 12 篇研发流程 SOP 文档供团队使用。 3. 扛责担当与客户导向： 结算信息支持修改回单付（C147.9）涉及资金计算且需 PC/H5 双端行为一致，主动识别并处理浮点精度、异常数据、移动端键盘限制等多类边界问题；C169.6 融合网货撮合运单横跨 TMS PC 端、物流 Web 端、货主移动端三端并行交付，按业务方诉求快速响应多轮调整（期间需求调整类变更 11 次），保障功能按期上线。 4. 人才发展与知识传承： 保持高频学习与输出，主动梳理 TMS 结算迁移、企服线二级频道配置等新技术难点并形成改动清单、方案文档与改动清单；建立 AI 辅助开发四端规则同步与知识库自动生成机制，将知识库维护从手工转为脚本产出，降低团队重复劳动成本。 | I12: 1、积极主动执行工作任务并主动做好团队成员间的协同分工，工作执行效果经常超出上级预期（90-100分） 2、按上级要求执行安排的工作任务，可以与团队成员做好协作分工，工作执行效果符合预期（80-89分） 3、未完全按上级要求执行工作任务，团队协作分工中表现一般，偶尔还需要在领导的指导下才可完成任务或偶尔不能完成任务（70-79分） 4、未完全按上级要求执行工作任务，团队协作性较差，需在领导的多次指导下才可完成或经常性的完不成任务（60-69分） 5、完全不按照上级的要求执行工作任务，完全没有团队协作意识，工作任务完成质量差或总是的不成任务（60分以下） | J12: 98 | M12: =J12*0.1+K12*0.9 -> 9.8 | N12: =(M12*F12+M13*F13+M14*F14+M15*F15+M16*F16+M17*F17)*0.8+L12*0.2 -> 0
C13: 主动思考与沟通 | E13: 主动思考工作内容、方法； 主动与工作对象沟通 | G13: 100 | I13: 1、独立主动思考问题解决办法，主动与工作伙伴进行沟通，沟通简明扼要，易于理解；（90-100分） 2、在上级的指引下才能思考出问题的解决办法，与工作伙伴基于工作任务的正常沟通，重点突出，较容易理解；（80-89分） 3、需要上级较多的指引共同思考问题的解决办法，与工作伙伴只是基于工作问题的沟通，沟通效果一般，需要重复说明，对方才能明白；（70-79分） 4、需要上级较多的指引共同思考问题的解决办法，与工作伙伴沟通较少，语言组织欠清晰，但尚能表达出意图，有时需要反复解释；（60-69分） 5、不能独立思考问题的解决办法，与工作伙伴沟通较少，口头表达含糊其辞，根本表达不清（60分以下） 根据员工思考问题及沟通方面的表现综合评分 | J13: 95 | M13: =J13*0.1+K13*0.9 -> 9.5
C14: 团队协作 | E14: 主动配合团队工作、分享产品经验 / 知识（如内部分享、案例输出）、协助同事解决工作难题的表现 | G14: 100 | I14: 1：主动发起团队协作，高频分享有价值经验，积极协助同事解决复杂难题，成为团队协作核心角色（90-100分） 2：积极配合团队安排，主动分享经验，能协助同事解决常规难题，无协作推诿情况（80-89分） 3：配合团队基础协作要求，偶尔分享经验，同事求助时能提供基础协助，无明显协作问题（70-79分） 4：被动参与协作，较少分享经验，同事求助时响应消极，存在轻微协作推诿（60-69 分） 5：拒绝配合团队协作，不分享经验，回避同事求助，严重影响团队协作效率（60分以下） | J14: 95 | M14: =J14*0.1+K14*0.9 -> 9.5
C15: 扛责担当 | E15: 面对工作问题（如需求偏差、项目风险）的态度，及关键任务的承接表现 | G15: 100 | I15: 1：主动发现并承担问题责任，积极推动解决方案，主动争抢关键 / 困难任务，不回避挑战（90-100分） 2：不推诿已发现的问题责任，能配合推动解决，关键任务安排后能积极承接，不抱怨（80-89分） 3：不主动承担额外责任，但自身负责范围内的问题不推诿，关键任务安排后能接受，无明显抵触（70-79分） 4：自身负责范围内的问题偶尔推诿，关键任务安排后被动接受，存在抱怨情绪（60-69 分） 5：频繁推诿各类问题责任，拒绝承接关键任务，回避工作挑战，影响任务推进（60分以下） | J15: 95 | M15: =J15*0.1+K15*0.9 -> 9.5
C16: 客户导向 | E16: 关注业务方 / 用户需求，及基于反馈优化工作的表现 | G16: 100 | I16: 1：主动高频对接客户获取反馈，深度分析需求痛点，主动推动基于反馈的产品优化，获得客户高度认可（90-100分） 2：定期对接客户获取反馈，能分析反馈并推动基础优化，客户无负面评价（80-89分） 3：按要求对接客户获取反馈，能响应反馈并做简单调整，客户无明显负面评价（70-79分） 4：需提醒才对接客户，反馈收集不完整，仅部分响应反馈，客户存在轻微负面评价（60-69 分） 5. 拒绝对接客户，不收集反馈，无视客户需求，客户存在严重负面评价（60分以下） | J16: 95 | M16: =J16*0.1+K16*0.9 -> 9.5
C17: 人才发展 | E17: 带教新人、自我学习提升、知识传承的综合表现 | G17: 100 | I17: 1：主动带教新人并帮助其快速成长，自主规划高频学习（如课程、行业研究），主动输出高质量知识文档，成为团队学习 / 传承标杆（90-100分） 2：按要求带教新人并帮助其达标，有固定学习计划（如定期课程），按要求输出知识文档，无明显不足（80-89分） 3：带教新人时能解答疑问，有基础学习行为，能配合输出简单知识文档，基本达标（70-79分） 4：带教新人时敷衍解答，学习行为零散无计划，知识文档需多次催促才输出，质量较差（60-69 分） 5：拒绝带教新人，无学习行为，不输出知识文档，阻碍团队人才发展 / 知识传承（60分以下） | J17: 95 | M17: =J17*0.1+K17*0.9 -> 9.5
B18: 总分 | M18: =N4*0.3+N7*0.4+N12*0.3 -> 0
B19: 员工签字： 签字日期： | I19: 直接上级签字： 签字日期：

Sheet 测试岗
B1: 绩效评价表
B2: 姓名： 岗位： 部门：
B3: 评价维度 | C3: 权重（%） | D3: 成果总结 | E3: 自评 | F3: 上级评分 | G3: 最终得分 （上级评分*权重）
B4: 本部门重点项目贡献 | C4: 0.3 | D4: =测试岗明细!H4 -> 0 | F4: =测试岗明细!N4 -> 0 | G4: =F4*C4 -> 0
B5: 岗位核心职责完成情况 | C5: 0.4 | D5: =测试岗明细!H7 -> 0 | F5: =测试岗明细!N7 -> 0 | G5: =F5*C5 -> 0
B6: 价值观及行为（包括但不限于团队协作、扛责担当、客户导向、人才发展（包括带教新人、知识传承、自我学习与提升）等） | C6: 0.3 | D6: =测试岗明细!H12 -> 0 | F6: =测试岗明细!N12 -> 0 | G6: =F6*C6 -> 0
B7: 总分 | G7: =SUM(G4:G6) -> 0
B8: 员工签字： 签字日期： | D8: 直接上级签字： 签字日期：

Sheet 测试岗明细
B1: 绩效评价表
B2: 姓名： 岗位： 部门：
B3: 评价维度 | C3: 绩效指标 | D3: 整体权重 | E3: 指标定义/说明 | F3: 权重（%） | G3: 目标值 | H3: 成果总结 | I3: 评分标准 | J3: 自评 （百分制） | K3: 上级评分（百分制） | L3: 部门评分 | M3: 得分 | N3: 总分
B4: 本部门重点项目贡献 | C4: 项目/任务指标 | D4: 1 | E4: 工作任务按计划、交付标准完成率 | G4: 100 | I4: 满分100：包含以下二项内容： （一）工作任务完成率满分70 1、工作任务按计划完成率大于90% 60-70 2、工作任务按计划完成率 80%-90% 50-59 3、工作任务按计划完成率 70%-80% 40-49 4、工作任务按计划完成率 小于70% 40以下 （二）工作质量 满分30分，每个重大缺陷扣10分 大于3次重大缺陷时，（一）（二）两项均记为0分 | M4: =J4*0.1+K4*0.9 -> 0 | N4: =(M4*F4+M5*F5)*0.8+L4*0.2 -> 0
E5: 任务所属项目按计划、交付标准达成率 | G5: 100 | I5: 1、项目按时保质交付上线90-100 2、项目交付时间每次延迟时间小于10%扣5分，大于10%以上扣10分 说明：因新增，变更需求（PCR通过审核），按调整后的项目完成时间为准 | M5: =J5*0.1+K5*0.9 -> 0
B7: 岗位核心职责完成情况 | C7: 交付质量 | D7: 1 | E7: 用户体验、生产问题 | G7: 100 | I7: 交付质量，满分100 无生产问题，无用户体验问题，90-100分； 不构成生产问题，但对用户体验有影响，80-89分； 造成关键功能、数据影响，但快速修复，60-79分； 造成生产线事故，60分以下 | M7: =J7*0.1+K7*0.9 -> 0 | N7: =(M7*F7+M8*F8+M9*F9+M10*F10)*0.8+L7*0.2 -> 0
C8: 流程规范 | E8: 工作流程、规范符合度 | G8: 100 | I8: 依据产研部发布的《工作流程、规范》要求，每次不符合规范流程，以规范中的扣分标准执行；规范中未明确的情况，根据实际情况补充发布的规范扣分 | M8: =J8*0.1+K8*0.9 -> 0
C9: 测试覆盖率 | E9: 测试关键场景、回归测试覆盖达标率，依据《测试用例》 | G9: 100 | I9: 满分100 1、关键场景测试达标率100%保质完成测试100 2、每遗漏一个重要场景扣10分 3、因遗漏重要场景导致生产事故 0~60 | M9: =J9*0.1+K9*0.9 -> 0
E10: 测试文档的完整、有效、正确编制 | G10: 100 | I10: 满分100，每次不符合要求，至少扣5分 | M10: =J10*0.1+K10*0.9 -> 0
B12: 价值观及行为 | C12: 责任心与协作 | D12: 1 | E12: 工作职责与分工、高效协作、执行力、主动性 | G12: 100 | I12: 1、积极主动执行工作任务并主动做好团队成员间的协同分工，工作执行效果经常超出上级预期（90-100分） 2、按上级要求执行安排的工作任务，可以与团队成员做好协作分工，工作执行效果符合预期（80-89分） 3、未完全按上级要求执行工作任务，团队协作分工中表现一般，偶尔还需要在领导的指导下才可完成任务或偶尔不能完成任务（70-79分） 4、未完全按上级要求执行工作任务，团队协作性较差，需在领导的多次指导下才可完成或经常性的完不成任务（60-69分） 5、完全不按照上级的要求执行工作任务，完全没有团队协作意识，工作任务完成质量差或总是的不成任务（60分以下） | M12: =J12*0.1+K12*0.9 -> 0 | N12: =(M12*F12+M13*F13+M14*F14+M15*F15+M16*F16+M17*F17)*0.8+L12*0.2 -> 0
C13: 主动思考与沟通 | E13: 主动思考工作内容、方法； 主动与工作对象沟通 | G13: 100 | I13: 1、独立主动思考问题解决办法，主动与工作伙伴进行沟通，沟通简明扼要，易于理解；（90-100分） 2、在上级的指引下才能思考出问题的解决办法，与工作伙伴基于工作任务的正常沟通，重点突出，较容易理解；（80-89分） 3、需要上级较多的指引共同思考问题的解决办法，与工作伙伴只是基于工作问题的沟通，沟通效果一般，需要重复说明，对方才能明白；（70-79分） 4、需要上级较多的指引共同思考问题的解决办法，与工作伙伴沟通较少，语言组织欠清晰，但尚能表达出意图，有时需要反复解释；（60-69分） 5、不能独立思考问题的解决办法，与工作伙伴沟通较少，口头表达含糊其辞，根本表达不清（60分以下） 根据员工思考问题及沟通方面的表现综合评分 | M13: =J13*0.1+K13*0.9 -> 0
C14: 团队协作 | E14: 主动配合团队工作、分享产品经验 / 知识（如内部分享、案例输出）、协助同事解决工作难题的表现 | G14: 100 | I14: 1：主动发起团队协作，高频分享有价值经验，积极协助同事解决复杂难题，成为团队协作核心角色（90-100分） 2：积极配合团队安排，主动分享经验，能协助同事解决常规难题，无协作推诿情况（80-89分） 3：配合团队基础协作要求，偶尔分享经验，同事求助时能提供基础协助，无明显协作问题（70-79分） 4：被动参与协作，较少分享经验，同事求助时响应消极，存在轻微协作推诿（60-69 分） 5：拒绝配合团队协作，不分享经验，回避同事求助，严重影响团队协作效率（60分以下） | M14: =J14*0.1+K14*0.9 -> 0
C15: 扛责担当 | E15: 面对工作问题（如需求偏差、项目风险）的态度，及关键任务的承接表现 | G15: 100 | I15: 1：主动发现并承担问题责任，积极推动解决方案，主动争抢关键 / 困难任务，不回避挑战（90-100分） 2：不推诿已发现的问题责任，能配合推动解决，关键任务安排后能积极承接，不抱怨（80-89分） 3：不主动承担额外责任，但自身负责范围内的问题不推诿，关键任务安排后能接受，无明显抵触（70-79分） 4：自身负责范围内的问题偶尔推诿，关键任务安排后被动接受，存在抱怨情绪（60-69 分） 5：频繁推诿各类问题责任，拒绝承接关键任务，回避工作挑战，影响任务推进（60分以下） | M15: =J15*0.1+K15*0.9 -> 0
C16: 客户导向 | E16: 关注业务方 / 用户需求，及基于反馈优化工作的表现 | G16: 100 | I16: 1：主动高频对接客户获取反馈，深度分析需求痛点，主动推动基于反馈的产品优化，获得客户高度认可（90-100分） 2：定期对接客户获取反馈，能分析反馈并推动基础优化，客户无负面评价（80-89分） 3：按要求对接客户获取反馈，能响应反馈并做简单调整，客户无明显负面评价（70-79分） 4：需提醒才对接客户，反馈收集不完整，仅部分响应反馈，客户存在轻微负面评价（60-69 分） 5. 拒绝对接客户，不收集反馈，无视客户需求，客户存在严重负面评价（60分以下） | M16: =J16*0.1+K16*0.9 -> 0
C17: 人才发展 | E17: 带教新人、自我学习提升、知识传承的综合表现 | G17: 100 | I17: 1：主动带教新人并帮助其快速成长，自主规划高频学习（如课程、行业研究），主动输出高质量知识文档，成为团队学习 / 传承标杆（90-100分） 2：按要求带教新人并帮助其达标，有固定学习计划（如定期课程），按要求输出知识文档，无明显不足（80-89分） 3：带教新人时能解答疑问，有基础学习行为，能配合输出简单知识文档，基本达标（70-79分） 4：带教新人时敷衍解答，学习行为零散无计划，知识文档需多次催促才输出，质量较差（60-69 分） 5：拒绝带教新人，无学习行为，不输出知识文档，阻碍团队人才发展 / 知识传承（60分以下） | M17: =J17*0.1+K17*0.9 -> 0
B18: 总分 | M18: =N4*0.3+N7*0.4+N12*0.3 -> 0
B19: 员工签字： 签字日期： | I19: 直接上级签字： 签字日期：

Sheet 安全运维岗
B1: 绩效评价表
B2: 姓名： 岗位： 部门：
B3: 评价维度 | C3: 权重（%） | D3: 成果总结 | E3: 自评 | F3: 上级评分 | G3: 最终得分 （上级评分*权重）
B4: 本部门重点项目贡献 | C4: 0.3 | D4: =安全运维岗明细!H4 -> 0 | F4: =安全运维岗明细!N4 -> 0 | G4: =F4*C4 -> 0
B5: 岗位核心职责完成情况 | C5: 0.4 | D5: =安全运维岗明细!H6 -> 0 | F5: =安全运维岗明细!N6 -> 0 | G5: =F5*C5 -> 0
B6: 价值观及行为（包括但不限于团队协作、扛责担当、客户导向、人才发展（包括带教新人、知识传承、自我学习与提升）等） | C6: 0.3 | D6: =安全运维岗明细!H13 -> 0 | F6: =安全运维岗明细!N13 -> 0 | G6: =F6*C6 -> 0
B7: 总分 | G7: =SUM(G4:G6) -> 0
B8: 员工签字： 签字日期： | D8: 直接上级签字： 签字日期：

Sheet 安全运维岗明细
B1: 绩效评价表
B2: 姓名： 岗位： 部门：
B3: 评价维度 | C3: 绩效指标 | D3: 整体权重 | E3: 指标定义/说明 | F3: 权重（%） | G3: 目标值 | H3: 成果总结 | I3: 评分标准 | J3: 自评 （百分制） | K3: 上级评分（百分制） | L3: 部门评分 | M3: 得分 | N3: 总分
B4: 本部门重点项目贡献 | C4: 项目/任务指标 | D4: 1 | E4: 依据《运维组季度工作任务计划》的工作目标按计划、交付标准完成率 | G4: 100 | I4: 满分100：包含以下二项内容： （一）工作任务完成率满分70 1、工作任务按计划完成率大于90% 60-70 2、工作任务按计划完成率 80%-90% 50-59 3、工作任务按计划完成率 70%-80% 40-49 4、工作任务按计划完成率 小于70% 40以下 （二）工作质量 满分30分，每个重大缺陷扣10分 大于3次重大缺陷时，（一）（二）两项均记为0分 | M4: =J4*0.1+K4*0.9 -> 0 | N4: =(M4*F4)*0.8+L4*0.2 -> 0
B6: 岗位核心职责完成情况 | C6: 系统运维 | D6: 1 | E6: 生产系统/UAT之数据库运行状况监控 | G6: 100 | I6: 满分100： 1、工作执行不到位，导致非阻断性问题，每次扣10分 2、导致重大问题，一次至少扣20分 3、每月执行良好，当月无扣分情况，加10分 | M6: =J6*0.1+K6*0.9 -> 0 | N6: =(M6*F6+M7*F7+M8*F8+M9*F9+M10*F10+M11*F11)*0.8+L6*0.2 -> 0
E7: 生产系统/UAT之数据库脚本审核，优化 | G7: 100 | I7: 满分100，每次不符合要求，至少扣5分 | M7: =J7*0.1+K7*0.9 -> 0
E8: 用友NC数据库的日常运维及月度巡检 | G8: 100 | I8: 满分100，每次不符合要求，至少扣5分 | M8: =J8*0.1+K8*0.9 -> 0
C9: 数据管理 | E9: 理解现有业务，规划数据域划分，及相关落地实施工作 | G9: 100 | I9: 满分100：保质完成100/影响体验，无重大影响80/造成关键功能、数据影响，快速修复60/造成生产线事故0~40 | M9: =J9*0.1+K9*0.9 -> 0
C10: 其他工作 | E10: 运维组其他工作 | G10: 100 | I10: 满分100，每次不符合要求，至少扣5分 | M10: =J10*0.1+K10*0.9 -> 0
C11: 流程规范 | E11: 工作流程、规范符合度 | G11: 100 | I11: 每次不符合规范流程，至少扣10分 | M11: =J11*0.1+K11*0.9 -> 0
B13: 价值观及行为 | C13: 责任心与协作 | D13: 1 | E13: 基于工作职责与分工，自主工作，高效协作 | G13: 100 | I13: 1、积极主动执行工作任务并主动做好团队成员间的协同分工，工作执行效果经常超出上级预期（90-100分） 2、按上级要求执行安排的工作任务，可以与团队成员做好协作分工，工作执行效果符合预期（80-89分） 3、未完全按上级要求执行工作任务，团队协作分工中表现一般，偶尔还需要在领导的指导下才可完成任务或偶尔不能完成任务（70-79分） 4、未完全按上级要求执行工作任务，团队协作性较差，需在领导的多次指导下才可完成或经常性的完不成任务（60-69分） 5、完全不按照上级的要求执行工作任务，完全没有团队协作意识，工作任务完成质量差或总是的不成任务（60分以下） | M13: =J13*0.1+K13*0.9 -> 0 | N13: =(M13*F13+M14*F14+M15*F15+M16*F16+M17*F17+M18*F18)*0.8+L13*0.2 -> 0
C14: 主动思考与沟通 | E14: 主动思考工作内容、方法；主动与工作对象沟通 | G14: 100 | I14: 1、独立主动思考问题解决办法，主动与工作伙伴进行沟通，沟通简明扼要，易于理解；（90-100分） 2、在上级的指引下才能思考出问题的解决办法，与工作伙伴基于工作任务的正常沟通，重点突出，较容易理解；（80-89分） 3、需要上级较多的指引共同思考问题的解决办法，与工作伙伴只是基于工作问题的沟通，沟通效果一般，需要重复说明，对方才能明白；（70-79分） 4、需要上级较多的指引共同思考问题的解决办法，与工作伙伴沟通较少，语言组织欠清晰，但尚能表达出意图，有时需要反复解释；（60-69分） 5、不能独立思考问题的解决办法，与工作伙伴沟通较少，口头表达含糊其辞，根本表达不清（60分以下） 根据员工思考问题及沟通方面的表现综合评分 | M14: =J14*0.1+K14*0.9 -> 0
C15: 团队协作 | E15: 主动配合团队工作、分享产品经验 / 知识（如内部分享、案例输出）、协助同事解决工作难题的表现 | G15: 100 | I15: 1：主动发起团队协作，高频分享有价值经验，积极协助同事解决复杂难题，成为团队协作核心角色（90-100分） 2：积极配合团队安排，主动分享经验，能协助同事解决常规难题，无协作推诿情况（80-89分） 3：配合团队基础协作要求，偶尔分享经验，同事求助时能提供基础协助，无明显协作问题（70-79分） 4：被动参与协作，较少分享经验，同事求助时响应消极，存在轻微协作推诿（60-69 分） 5：拒绝配合团队协作，不分享经验，回避同事求助，严重影响团队协作效率（60分以下） | M15: =J15*0.1+K15*0.9 -> 0
C16: 扛责担当 | E16: 面对工作问题（如需求偏差、项目风险）的态度，及关键任务的承接表现 | G16: 100 | I16: 1：主动发现并承担问题责任，积极推动解决方案，主动争抢关键 / 困难任务，不回避挑战（90-100分） 2：不推诿已发现的问题责任，能配合推动解决，关键任务安排后能积极承接，不抱怨（80-89分） 3：不主动承担额外责任，但自身负责范围内的问题不推诿，关键任务安排后能接受，无明显抵触（70-79分） 4：自身负责范围内的问题偶尔推诿，关键任务安排后被动接受，存在抱怨情绪（60-69 分） 5：频繁推诿各类问题责任，拒绝承接关键任务，回避工作挑战，影响任务推进（60分以下） | M16: =J16*0.1+K16*0.9 -> 0
C17: 客户导向 | E17: 关注业务方 / 用户需求，及基于反馈优化工作的表现 | G17: 100 | I17: 1：主动高频对接客户获取反馈，深度分析需求痛点，主动推动基于反馈的产品优化，获得客户高度认可（90-100分） 2：定期对接客户获取反馈，能分析反馈并推动基础优化，客户无负面评价（80-89分） 3：按要求对接客户获取反馈，能响应反馈并做简单调整，客户无明显负面评价（70-79分） 4：需提醒才对接客户，反馈收集不完整，仅部分响应反馈，客户存在轻微负面评价（60-69 分） 5. 拒绝对接客户，不收集反馈，无视客户需求，客户存在严重负面评价（60分以下） | M17: =J17*0.1+K17*0.9 -> 0
C18: 人才发展 | E18: 带教新人、自我学习提升、知识传承的综合表现 | G18: 100 | I18: 1：主动带教新人并帮助其快速成长，自主规划高频学习（如课程、行业研究），主动输出高质量知识文档，成为团队学习 / 传承标杆（90-100分） 2：按要求带教新人并帮助其达标，有固定学习计划（如定期课程），按要求输出知识文档，无明显不足（80-89分） 3：带教新人时能解答疑问，有基础学习行为，能配合输出简单知识文档，基本达标（70-79分） 4：带教新人时敷衍解答，学习行为零散无计划，知识文档需多次催促才输出，质量较差（60-69 分） 5：拒绝带教新人，无学习行为，不输出知识文档，阻碍团队人才发展 / 知识传承（60分以下） | M18: =J18*0.1+K18*0.9 -> 0
B19: 总分 | N19: =N4*0.3+N6*0.4+N13*0.3 -> 0
B20: 员工签字： 签字日期： | I20: 直接上级签字： 签字日期：

Sheet 设计岗
B1: 绩效评价表
B2: 姓名： 岗位： 部门：
B3: 评价维度 | C3: 权重（%） | D3: 成果总结 | E3: 自评 | F3: 上级评分 | G3: 最终得分 （上级评分*权重）
B4: 本部门重点项目贡献 | C4: 0.3 | D4: =设计岗明细!I4 -> 0 | F4: =设计岗明细!O4 -> 0 | G4: =F4*C4 -> 0
B5: 岗位核心职责完成情况 | C5: 0.4 | D5: =设计岗明细!I6 -> 0 | F5: =设计岗明细!O6 -> 0 | G5: =F5*C5 -> 0
B6: 价值观及行为（包括但不限于团队协作、扛责担当、客户导向、人才发展（包括带教新人、知识传承、自我学习与提升）等） | C6: 0.3 | D6: =设计岗明细!I11 -> 0 | F6: =设计岗明细!O11 -> 0 | G6: =F6*C6 -> 0
B7: 总分 | G7: =SUM(G4:G6) -> 0
B8: 员工签字： 签字日期： | D8: 直接上级签字： 签字日期：

Sheet 设计岗明细
C1: 绩效评价表
C2: 姓名： 岗位： 部门：
C3: 评价维度 | D3: 绩效指标 | E3: 整体权重 | F3: 指标定义/说明 | G3: 权重（%） | H3: 目标值 | I3: 成果总结 | J3: 评分标准 | K3: 自评 （百分制） | L3: 上级评分（百分制） | M3: 部门评分 | N3: 得分 | O3: 总分
C4: 本部门重点项目贡献 | D4: 任务目标达成率 | E4: 1 | F4: 按时保质完成UI设计，交互设计 | H4: 100 | J4: 满分100： 1：按时完成或超额完成（90-100分） 2：工作完成80%以上（80-89分） 3：由于个人原因未完成工作（60-79分） 4：工作严重延迟（0-59分） | N4: =K4*0.1+L4*0.9 -> 0 | O4: =(N4*G4)*0.8+M4*0.2 -> 0
C6: 岗位核心职责完成情况 | D6: 需求认可度 | E6: 1 | F6: 需求方针对交付成果的认可程度 | H6: 100 | J6: 满分100 根据设计的视觉效果、交互的流畅性。 因客观技术原因，如网络、设备原因造成实施效果差除外。 | N6: =K6*0.1+L6*0.9 -> 0 | O6: =(N6*G6+N7*G7+N8*G8+N9*G9)*0.8+M6*0.2 -> 0
D7: 工作能力 | F7: 沟通能力 | H7: 100 | J7: 1：具有出色的口头沟通技巧，简明扼要，易于理解；（90-100分） 2：口头沟通能够表达出意图，重点突出，较容易理解；（80-89分） 3：口头沟通基本能够表达意图，重点比较突出，偶尔需要重复说明；（70-79分） 4：口头表达语言组织欠清晰，但尚能表达出意图，有时需要反复解释；（60-69分） 5：口头表达含糊其辞，根本表达不清（60分以下） | N7: =K7*0.1+L7*0.9 -> 0
F8: 执行能力 | H8: 100 | J8: 1：具有出色的执行力，无需上级指导，执行效果经常超出上级的想象（90-100分） 2：具有较强的执行力，在上级的指导下，能够完成任务，执行效果很好（80-89分） 3：执行力可满足岗位的要求，但缺乏独立思考和计划的能力，需要上级在方法上给予支持，执行效果较好（70-79分） 4：执行力一般，偶尔有推脱或畏难现象，执行过程经常需要上级的帮助，执行效果一般（60-69分） 5：初步具有执行意识，但执行延迟，经常出现推脱或畏难现象，需要特别关注和帮助，执行力较弱（60分以下） | N8: =K8*0.1+L8*0.9 -> 0
F9: 业务能力和水平 | H9: 100 | J9: 1：精通本岗位所要求的理论知识和专业技能（90-100分） 2：全面了解并较好的掌握与本岗位有关的理论知识和专业技能（80-89分） 3：基本掌握与本岗位有关的专业知识，对本岗位业务有一定了解，但尚需提高（70-79分） 4：对本岗位专业知识有一定了解，但不够深入（60-69分） 5：业务知识欠缺，业务生疏，经常出现失误（60分以下） | N9: =K9*0.1+L9*0.9 -> 0
C11: 价值观及行为 | D11: 工作态度 | E11: 1 | F11: 工作的态度 | H11: 100 | J11: 1：积极主动承担各种工作任务，完成过程中有自己的思考，可提出自己独到的想法（90-100分） 2：对于领导交待的任务不折不扣的执行，积极主动解决过程中的各种问题（80-89分） 3：对于领导交待的任务积极的执行，偶尔需要在领导的指导下才可顺利完成（70-79分） 4：对于领导交待的任务，大多接受的较为被动，需在领导的多次指导下才可完成（60-69分） 5：完全被动的接受任务，主动性欠缺，任务完成质量较差（60分以下） | N11: =K11*0.1+L11*0.9 -> 0 | O11: =(N11*G11+N12*G12+N13*G13+N14*G14+N15*G15)*0.8+M11*0.2 -> 0
D12: 团队协作 | F12: 主动配合团队工作、分享产品经验 / 知识（如内部分享、案例输出）、协助同事解决工作难题的表现 | H12: 100 | J12: 1：主动发起团队协作，高频分享有价值经验，积极协助同事解决复杂难题，成为团队协作核心角色（90-100分） 2：积极配合团队安排，主动分享经验，能协助同事解决常规难题，无协作推诿情况（80-89分） 3：配合团队基础协作要求，偶尔分享经验，同事求助时能提供基础协助，无明显协作问题（70-79分） 4：被动参与协作，较少分享经验，同事求助时响应消极，存在轻微协作推诿（60-69 分） 5：拒绝配合团队协作，不分享经验，回避同事求助，严重影响团队协作效率（60分以下） | N12: =K12*0.1+L12*0.9 -> 0
D13: 扛责担当 | F13: 面对工作问题（如需求偏差、项目风险）的态度，及关键任务的承接表现 | H13: 100 | J13: 1：主动发现并承担问题责任，积极推动解决方案，主动争抢关键 / 困难任务，不回避挑战（90-100分） 2：不推诿已发现的问题责任，能配合推动解决，关键任务安排后能积极承接，不抱怨（80-89分） 3：不主动承担额外责任，但自身负责范围内的问题不推诿，关键任务安排后能接受，无明显抵触（70-79分） 4：自身负责范围内的问题偶尔推诿，关键任务安排后被动接受，存在抱怨情绪（60-69 分） 5：频繁推诿各类问题责任，拒绝承接关键任务，回避工作挑战，影响任务推进（60分以下） | N13: =K13*0.1+L13*0.9 -> 0
D14: 客户导向 | F14: 关注业务方 / 用户需求，及基于反馈优化工作的表现 | H14: 100 | J14: 1：主动高频对接客户获取反馈，深度分析需求痛点，主动推动基于反馈的产品优化，获得客户高度认可（90-100分） 2：定期对接客户获取反馈，能分析反馈并推动基础优化，客户无负面评价（80-89分） 3：按要求对接客户获取反馈，能响应反馈并做简单调整，客户无明显负面评价（70-79分） 4：需提醒才对接客户，反馈收集不完整，仅部分响应反馈，客户存在轻微负面评价（60-69 分） 5. 拒绝对接客户，不收集反馈，无视客户需求，客户存在严重负面评价（60分以下） | N14: =K14*0.1+L14*0.9 -> 0
D15: 人才发展 | F15: 带教新人、自我学习提升、知识传承的综合表现 | H15: 100 | J15: 1：主动带教新人并帮助其快速成长，自主规划高频学习（如课程、行业研究），主动输出高质量知识文档，成为团队学习 / 传承标杆（90-100分） 2：按要求带教新人并帮助其达标，有固定学习计划（如定期课程），按要求输出知识文档，无明显不足（80-89分） 3：带教新人时能解答疑问，有基础学习行为，能配合输出简单知识文档，基本达标（70-79分） 4：带教新人时敷衍解答，学习行为零散无计划，知识文档需多次催促才输出，质量较差（60-69 分） 5：拒绝带教新人，无学习行为，不输出知识文档，阻碍团队人才发展 / 知识传承（60分以下） | N15: =K15*0.1+L15*0.9 -> 0
C16: 总分 | N16: =O4*0.3+O6*0.4+O11*0.3 -> 0
C17: 员工签字： 签字日期： | H17: 直接上级签字： 签字日期：

Sheet 项管岗
B1: 绩效评价表
B2: 姓名： 岗位： 部门：
B3: 评价维度 | C3: 权重（%） | D3: 成果总结 | E3: 自评 | F3: 上级评分 | G3: 最终得分 （上级评分*权重）
B4: 本部门重点项目贡献 | C4: 0.3 | D4: =项管岗明细!H4 -> 0 | F4: =项管岗明细!N4 -> 0 | G4: =F4*C4 -> 0
B5: 岗位核心职责完成情况 | C5: 0.4 | D5: =项管岗明细!H8 -> 0 | F5: =项管岗明细!N8 -> 0 | G5: =F5*C5 -> 0
B6: 价值观及行为（包括但不限于团队协作、扛责担当、客户导向、人才发展（包括带教新人、知识传承、自我学习与提升）等） | C6: 0.3 | D6: =项管岗明细!H13 -> 0 | F6: =项管岗明细!N13 -> 0 | G6: =F6*C6 -> 0
B7: 总分 | G7: =SUM(G4:G6) -> 0
B8: 员工签字： 签字日期： | D8: 直接上级签字： 签字日期：

Sheet 项管岗明细
B1: 绩效评价表
B2: 姓名： 岗位： 部门：
B3: 评价维度 | C3: 绩效指标 | D3: 整体权重 | E3: 指标定义/说明 | F3: 权重（%） | G3: 目标值 | H3: 成果总结 | I3: 评分标准 | J3: 自评 （百分制） | K3: 上级评分（百分制） | L3: 部门评分 | M3: 得分 | N3: 总分
B4: 本部门重点项目贡献 | C4: 任务目标达成率 | D4: 1 | E4: 核心目标达成率（衡量项目经理所负责的重点项目在既定周期内，是否按计划完成里程碑节点、交付物及核心KPI） | G4: 100 | I4: 满分100： 90-100分（卓越）：所有重点项目均按计划或超前完成核心目标；关键结果（KRs）达成率≥110%；在遇到重大风险时，仍能通过有效手段确保结果超出预期。 75-89分（优秀）：核心目标整体达成，关键结果达成率在 95%-109% 之间；虽有部分非关键节点延期或微调，但未影响最终交付质量与业务价值。 60-74分（合格）：核心目标基本达成，关键结果达成率在 80%-94% 之间；存在1-2项次要目标未完成，或主要节点有延期但通过赶工补救。 60分以下（待改进）：核心目标未达成，关键结果达成率低于80%；出现重大里程碑延期、关键交付物缺失或项目结果未通过验收。 | M4: =J4*0.1+K4*0.9 -> 0 | N4: =(M4*F4+M5*F5+M6*F6)*0.8+L4*0.2 -> 0
C5: 设计与文档输出 | E5: 跨部门协同与资源整合效能（衡量项目经理在推动项目过程中，打破部门壁垒、整合内外部资源、协调解决冲突的效率与质量，以及上下游部门的满意度。） | G5: 100 | I5: 满分100 90-100分（卓越）：主动建立高效的跨部门协作机制，能提前预判并化解资源冲突；在关键资源获取或跨部门配合上获得强力支持，项目推动顺畅；相关部门满意度评分 ≥95分。 75-89分（优秀）：能有效协调跨部门资源，未因协同问题导致项目停滞；出现的一般性资源冲突能在3个工作日内解决；相关部门满意度评分在 85-94分。 60-74分（合格）：基本能协调所需资源，但偶尔因沟通不畅导致5个工作日以上的延误；需要上级介入才能解决部分跨部门争议；相关部门满意度评分在 70-84分。 60分以下（待改进）：多次因跨部门推诿或资源协调不力导致项目关键路径受阻；经常因沟通问题引发部门间矛盾，影响团队士气；相关部门满意度评分 低于70分。 | M5: =J5*0.1+K5*0.9 -> 0
C6: 知识分享 | E6: 战略价值与过程资产沉淀（衡量项目成果对部门/公司的战略支撑度，以及在项目过程中知识沉淀、流程优化、风险防控机制建设的贡献。） | G6: 100 | I6: 满分100： 90-100分（卓越）：项目成果直接支撑部门或公司一级战略落地，形成可复用的标准化流程、工具或方法论并在部门内推广；成功沉淀关键过程资产，显著提升后续同类项目效率 ≥20%；或有效规避了重大潜在风险（如合规、安全）。 75-89分（优秀）：项目成果符合部门战略方向；完成项目复盘，产出了有价值的复盘报告或案例库；建立了较为完善的项目文档管理体系，对后续工作有较好的参考价值。 60-74分（合格）：项目成果与部门战略方向无偏离；按要求提交了项目总结和必要的文档，但资产沉淀较为零散，复用性一般；无重大过程资产遗失。 60分以下（待改进）：项目成果与部门战略关联度低；未进行有效的项目复盘，关键文档缺失严重；或因过程管理不当导致重复出现同类低级错误。 | M6: =J6*0.1+K6*0.9 -> 0
B8: 岗位核心职责完成情况 | C8: 制度与规范执行 | D8: 1 | E8: 严格执行公司、部门制度与规范 | G8: 100 | I8: 满分100： 1:优严格执行公司和部门制度与规范，无违规行为，积极配合上级安排，绩效突出，对公司发展做出了重要贡献（90-100） 2:大部分时间严格执行公司和部门制度与规范，偶有违规行为但及时改正，工作表现稳定，对公司发展有一定贡献（80-89） 3:一般地执行公司和部门制度与规范，偶有违规行为，需要改进，工作表现一般，对公司发展贡献有限（60-79） 4:经常违反公司和部门制度与规范，严重影响团队和公司的正常运转，需要立即改进，工作表现较差，对公司发展没有贡献（50-59） 5:严重违反公司和部门制度与规范，严重影响公司形象和利益，造成重大损失，需要立即纠正，对公司发展没有任何贡献（0-49） | M8: =J8*0.1+K8*0.9 -> 0 | N8: =(M8*F8+M9*F9+M10*F10+F11*M11)*0.8+L8*0.2 -> 0
C9: 工作能力 | E9: 沟通能力 | G9: 100 | I9: 1：具有出色的口头沟通技巧，简明扼要，易于理解（90-100分） 2：口头沟通能够表达出意图，重点突出，较容易理解（80-89分） 3：口头沟通基本能够表达意图，重点比较突出，偶尔需要重复说明（70-79分） 4：口头表达语言组织欠清晰，但尚能表达出意图，有时需要反复解释（60-69分） 5：口头表达含糊其辞，根本表达不清（60分以下） | M9: =J9*0.1+K9*0.9 -> 0
E10: 执行能力 | G10: 100 | I10: 1：具有出色的执行力，无需上级指导，执行效果经常超出上级的想象（90-100分） 2：具有较强的执行力，在上级的指导下，能够完成任务，执行效果很好（80-89分） 3：执行力可满足岗位的要求，但缺乏独立思考和计划的能力，需要上级在方法上给予支持，执行效果较好（70-79分） 4：执行力一般，偶尔有推脱或畏难现象，执行过程经常需要上级的帮助，执行效果一般（60-69分） 5：初步具有执行意识，但执行延迟，经常出现推脱或畏难现象，需要特别关注和帮助，执行力较弱（60分以下） | M10: =J10*0.1+K10*0.9 -> 0
E11: 业务能力和水平 | G11: 100 | I11: 1：精通本岗位所要求的理论知识和专业技能（90-100分） 2：全面了解并较好的掌握与本岗位有关的理论知识和专业技能（80-89分） 3：基本掌握与本岗位有关的专业知识，对本岗位业务有一定了解，但尚需提高（70-79分） 4：对本岗位专业知识有一定了解，但不够深入（60-69分） 5：业务知识欠缺，业务生疏，经常出现失误（60分以下） | M11: =J11*0.1+K11*0.9 -> 0
B13: 价值观及行为 | C13: 工作态度 | D13: 1 | E13: 工作的态度 | G13: 100 | I13: 1：积极主动承担各种工作任务，完成过程中有自己的思考，可提出自己独到的想法（90-100分） 2：对于领导交待的任务不折不扣的执行，积极主动解决过程中的各种问题（80-89分） 3：对于领导交待的任务积极的执行，偶尔需要在领导的指导下才可顺利完成（70-79分） 4：对于领导交待的任务，大多接受的较为被动，需在领导的多次指导下才可完成（60-69分） 5：完全被动的接受任务，主动性欠缺，任务完成质量较差（60分以下） | M13: =J13*0.1+K13*0.9 -> 0 | N13: =(M13*F13+M14*F14+M15*F15+M16*F16+M17*F17)*0.8+L13*0.2 -> 0
C14: 团队协作 | E14: 主动配合团队工作、分享产品经验 / 知识（如内部分享、案例输出）、协助同事解决工作难题的表现 | G14: 100 | I14: 1：主动发起团队协作，高频分享有价值经验，积极协助同事解决复杂难题，成为团队协作核心角色（90-100分） 2：积极配合团队安排，主动分享经验，能协助同事解决常规难题，无协作推诿情况（80-89分） 3：配合团队基础协作要求，偶尔分享经验，同事求助时能提供基础协助，无明显协作问题（70-79分） 4：被动参与协作，较少分享经验，同事求助时响应消极，存在轻微协作推诿（60-69 分） 5：拒绝配合团队协作，不分享经验，回避同事求助，严重影响团队协作效率（60分以下） | M14: =J14*0.1+K14*0.9 -> 0
C15: 扛责担当 | E15: 面对工作问题（如需求偏差、项目风险）的态度，及关键任务的承接表现 | G15: 100 | I15: 1：主动发现并承担问题责任，积极推动解决方案，主动争抢关键 / 困难任务，不回避挑战（90-100分） 2：不推诿已发现的问题责任，能配合推动解决，关键任务安排后能积极承接，不抱怨（80-89分） 3：不主动承担额外责任，但自身负责范围内的问题不推诿，关键任务安排后能接受，无明显抵触（70-79分） 4：自身负责范围内的问题偶尔推诿，关键任务安排后被动接受，存在抱怨情绪（60-69 分） 5：频繁推诿各类问题责任，拒绝承接关键任务，回避工作挑战，影响任务推进（60分以下） | M15: =J15*0.1+K15*0.9 -> 0
C16: 客户导向 | E16: 关注业务方 / 用户需求，及基于反馈优化工作的表现 | G16: 100 | I16: 1：主动高频对接客户获取反馈，深度分析需求痛点，主动推动基于反馈的产品优化，获得客户高度认可（90-100分） 2：定期对接客户获取反馈，能分析反馈并推动基础优化，客户无负面评价（80-89分） 3：按要求对接客户获取反馈，能响应反馈并做简单调整，客户无明显负面评价（70-79分） 4：需提醒才对接客户，反馈收集不完整，仅部分响应反馈，客户存在轻微负面评价（60-69 分） 5. 拒绝对接客户，不收集反馈，无视客户需求，客户存在严重负面评价（60分以下） | M16: =J16*0.1+K16*0.9 -> 0
C17: 人才发展 | E17: 带教新人、自我学习提升、知识传承的综合表现 | G17: 100 | I17: 1：主动带教新人并帮助其快速成长，自主规划高频学习（如课程、行业研究），主动输出高质量知识文档，成为团队学习 / 传承标杆（90-100分） 2：按要求带教新人并帮助其达标，有固定学习计划（如定期课程），按要求输出知识文档，无明显不足（80-89分） 3：带教新人时能解答疑问，有基础学习行为，能配合输出简单知识文档，基本达标（70-79分） 4：带教新人时敷衍解答，学习行为零散无计划，知识文档需多次催促才输出，质量较差（60-69 分） 5：拒绝带教新人，无学习行为，不输出知识文档，阻碍团队人才发展 / 知识传承（60分以下） | M17: =J17*0.1+K17*0.9 -> 0
B18: 总分 | M18: =N4*0.3+N8*0.4+N13*0.3 -> 0
B19: 员工签字： 签字日期： | I19: 直接上级签字： 签字日期：

Sheet 知识产权岗
B1: 绩效评价表
B2: 姓名： 岗位： 部门：
B3: 评价维度 | C3: 权重（%） | D3: 成果总结 | E3: 自评 | F3: 上级评分 | G3: 最终得分 （上级评分*权重）
B4: 本部门重点项目贡献 | C4: 0.3 | D4: =[1]知识产权岗明细!H4 -> 0 | F4: =[1]知识产权岗明细!N4 -> 0 | G4: =F4*C4 -> 0
B5: 岗位核心职责完成情况 | C5: 0.4 | D5: =[1]知识产权岗明细!H8 -> 0 | F5: =[1]知识产权岗明细!N8 -> 0 | G5: =F5*C5 -> 0
B6: 价值观及行为（包括但不限于团队协作、扛责担当、客户导向、人才发展（包括带教新人、知识传承、自我学习与提升）等） | C6: 0.3 | D6: =[1]知识产权岗明细!H13 -> 0 | F6: =[1]知识产权岗明细!N13 -> 0 | G6: =F6*C6 -> 0
B7: 总分 | G7: =SUM(G4:G6) -> 0
B8: 员工签字： 签字日期： | D8: 直接上级签字： 签字日期：

Sheet 知识产权岗明细
B1: 绩效评价表
B2: 姓名： 岗位： 部门：
B3: 评价维度 | C3: 绩效指标 | D3: 整体权重 | E3: 指标定义/说明 | F3: 权重（%） | G3: 目标值 | H3: 成果总结 | I3: 评分标准 | J3: 自评 （百分制） | K3: 上级评分（百分制） | L3: 部门评分 | M3: 得分 | N3: 总分
B4: 本部门重点项目贡献 | C4: 处理所负责事业群的专利申请工作 | D4: 1 | E4: 按期保质完成相关事业群的专利申请文件 | F4: 0.4 | G4: 100 | I4: 满分100 专利文件撰写专业、精准，授权前景明朗。全程主动、高效管理，能优化流程，是团队标杆（90-100分） 能独立高质量完成全流程工作，结果可靠（80-89分） 能完成基本工作，但部分环节的深度、效率或质量有提升空间（70-79分） 仅能完成指令性工作，质量勉强达标，需频繁指导与复核（60-69分） 工作质量不达标，影响申请进程或公司利益（60分以下） | M4: =J4*0.1+K4*0.9 -> 0 | N4: =(M4*F4+M5*F5+M6*F6)*0.8+L4*0.2 -> 0
C5: 掌握相关知识产权情况，跟进立项项目组，形成专利布局建议及风险预警 | E5: 识别知识产权挖掘点及风险点，输出专利布局建议 | F5: 0.3 | G5: 100 | I5: 满分100 分析具有战略前瞻性，布局建议能直接塑造或影响产品技术路线，风险预警精准且解决方案完备（90-100分） 能独立产出有价值的布局分析和风险提示，对业务有明确助力（80-89分） 能完成基础的分析工作，但洞察深度和商业价值有限（70-79分） 仅能完成信息收集和简单汇总，分析与建议流于形式（60-69分） 未能履行基本职责，输出物错误或缺失，可能误导项目决策（60分以下） | M5: =J5*0.1+K5*0.9 -> 0
C6: 评审技术交底书，给出申报建议 | E6: 对技术交底书进行检索分析，形成申报建议 | F6: 0.3 | G6: 100 | I6: 满分100： 评审专业、权威，能显著提升发明质量，申报建议极具战略价值（90-100分） 能独立完成高质量的评审工作，建议明确合理（80-89分） 能完成基本评审流程，但在检索深度或建议的精准性上需加强（70-79分） 评审流程执行不到位，判断依据不足（60-69分） 评审工作失职，导致错误决策（60分以下） | M6: =J6*0.1+K6*0.9 -> 0
B8: 岗位核心职责完成情况 | C8: 制度与规范执行 | D8: 1 | E8: 严格执行公司、部门制度与规范 | F8: 0.3 | G8: 100 | I8: 满分100： 1:优严格执行公司和部门制度与规范，无违规行为，积极配合上级安排，绩效突出，对公司发展做出了重要贡献（90-100） 2:大部分时间严格执行公司和部门制度与规范，偶有违规行为但及时改正，工作表现稳定，对公司发展有一定贡献（80-89） 3:一般地执行公司和部门制度与规范，偶有违规行为，需要改进，工作表现一般，对公司发展贡献有限（60-79） 4:经常违反公司和部门制度与规范，严重影响团队和公司的正常运转，需要立即改进，工作表现较差，对公司发展没有贡献（50-59） 5:严重违反公司和部门制度与规范，严重影响公司形象和利益，造成重大损失，需要立即纠正，对公司发展没有任何贡献（0-49） | M8: =J8*0.1+K8*0.9 -> 0 | N8: =(M8*F8+M9*F9+M10*F10+F11*M11)*0.8+L8*0.2 -> 0
C9: 工作能力 | E9: 沟通能力 | F9: 0.2 | G9: 100 | I9: 1：具有出色的口头沟通技巧，简明扼要，易于理解（90-100分） 2：口头沟通能够表达出意图，重点突出，较容易理解（80-89分） 3：口头沟通基本能够表达意图，重点比较突出，偶尔需要重复说明（70-79分） 4：口头表达语言组织欠清晰，但尚能表达出意图，有时需要反复解释（60-69分） 5：口头表达含糊其辞，根本表达不清（60分以下） | M9: =J9*0.1+K9*0.9 -> 0
E10: 执行能力 | F10: 0.3 | G10: 100 | I10: 1：具有出色的执行力，无需上级指导，执行效果经常超出上级的想象（90-100分） 2：具有较强的执行力，在上级的指导下，能够完成任务，执行效果很好（80-89分） 3：执行力可满足岗位的要求，但缺乏独立思考和计划的能力，需要上级在方法上给予支持，执行效果较好（70-79分） 4：执行力一般，偶尔有推脱或畏难现象，执行过程经常需要上级的帮助，执行效果一般（60-69分） 5：初步具有执行意识，但执行延迟，经常出现推脱或畏难现象，需要特别关注和帮助，执行力较弱（60分以下） | M10: =J10*0.1+K10*0.9 -> 0
E11: 业务能力和水平 | F11: 0.2 | G11: 100 | I11: 1：精通本岗位所要求的理论知识和专业技能（90-100分） 2：全面了解并较好的掌握与本岗位有关的理论知识和专业技能（80-89分） 3：基本掌握与本岗位有关的专业知识，对本岗位业务有一定了解，但尚需提高（70-79分） 4：对本岗位专业知识有一定了解，但不够深入（60-69分） 5：业务知识欠缺，业务生疏，经常出现失误（60分以下） | M11: =J11*0.1+K11*0.9 -> 0
B13: 价值观及行为 | C13: 工作态度 | D13: 1 | E13: 工作的态度 | F13: 0.2 | G13: 100 | I13: 1：积极主动承担各种工作任务，完成过程中有自己的思考，可提出自己独到的想法（90-100分） 2：对于领导交待的任务不折不扣的执行，积极主动解决过程中的各种问题（80-89分） 3：对于领导交待的任务积极的执行，偶尔需要在领导的指导下才可顺利完成（70-79分） 4：对于领导交待的任务，大多接受的较为被动，需在领导的多次指导下才可完成（60-69分） 5：完全被动的接受任务，主动性欠缺，任务完成质量较差（60分以下） | M13: =J13*0.1+K13*0.9 -> 0 | N13: =(M13*F13+M14*F14+M15*F15+M16*F16+M17*F17)*0.8+L13*0.2 -> 0
C14: 团队协作 | E14: 主动配合团队工作、分享知识产权实操经验、协助同事解决工作难题的表现 | F14: 0.2 | G14: 100 | I14: 1：主动发起团队协作，高频分享有价值经验，积极协助同事解决复杂难题，成为团队协作核心角色（90-100分） 2：积极配合团队安排，主动分享经验，能协助同事解决常规难题，无协作推诿情况（80-89分） 3：配合团队基础协作要求，偶尔分享经验，同事求助时能提供基础协助，无明显协作问题（70-79分） 4：被动参与协作，较少分享经验，同事求助时响应消极，存在轻微协作推诿（60-69 分） 5：拒绝配合团队协作，不分享经验，回避同事求助，严重影响团队协作效率（60分以下） | M14: =J14*0.1+K14*0.9 -> 0
C15: 扛责担当 | E15: 面对工作问题（如需求偏差、项目风险）的态度，及关键任务的承接表现 | F15: 0.2 | G15: 100 | I15: 1：主动发现并承担问题责任，积极推动解决方案，主动争抢关键 / 困难任务，不回避挑战（90-100分） 2：不推诿已发现的问题责任，能配合推动解决，关键任务安排后能积极承接，不抱怨（80-89分） 3：不主动承担额外责任，但自身负责范围内的问题不推诿，关键任务安排后能接受，无明显抵触（70-79分） 4：自身负责范围内的问题偶尔推诿，关键任务安排后被动接受，存在抱怨情绪（60-69 分） 5：频繁推诿各类问题责任，拒绝承接关键任务，回避工作挑战，影响任务推进（60分以下） | M15: =J15*0.1+K15*0.9 -> 0
C16: 客户导向 | E16: 关注业务方 / 用户需求，及基于反馈优化工作的表现 | F16: 0.2 | G16: 100 | I16: 1：主动高频对接客户获取反馈，深度分析需求痛点，主动推动基于反馈的产品优化，获得客户高度认可（90-100分） 2：定期对接客户获取反馈，能分析反馈并推动基础优化，客户无负面评价（80-89分） 3：按要求对接客户获取反馈，能响应反馈并做简单调整，客户无明显负面评价（70-79分） 4：需提醒才对接客户，反馈收集不完整，仅部分响应反馈，客户存在轻微负面评价（60-69 分） 5. 拒绝对接客户，不收集反馈，无视客户需求，客户存在严重负面评价（60分以下） | M16: =J16*0.1+K16*0.9 -> 0
C17: 人才发展 | E17: 带教新人、自我学习提升、知识传承的综合表现 | F17: 0.2 | G17: 100 | I17: 1：主动带教新人并帮助其快速成长，自主规划高频学习（如课程、行业研究），主动输出高质量知识文档，成为团队学习 / 传承标杆（90-100分） 2：按要求带教新人并帮助其达标，有固定学习计划（如定期课程），按要求输出知识文档，无明显不足（80-89分） 3：带教新人时能解答疑问，有基础学习行为，能配合输出简单知识文档，基本达标（70-79分） 4：带教新人时敷衍解答，学习行为零散无计划，知识文档需多次催促才输出，质量较差（60-69 分） 5：拒绝带教新人，无学习行为，不输出知识文档，阻碍团队人才发展 / 知识传承（60分以下） | M17: =J17*0.1+K17*0.9 -> 0
B18: 总分 | M18: =N4*0.3+N8*0.4+N13*0.3 -> 0
B19: 员工签字： 签字日期： | I19: 直接上级签字： 签字日期：
